{
  "title": "Tabs",
  "description": "The Tabs component provides a customizable and smooth tab navigation system, supporting multiple sizes and theme-aware applications, perfect for modern UIs with light and dark modes.",
  "date": "2025-03-12T00:00:00.000Z",
  "body": {
    "raw": "\n# Tabs Component Documentation\n\nThe **Tabs** component is a customizable tab system that supports multiple sizes and provides a smooth transition effect. It is designed for modern, theme-aware applications that use CSS variables (defined in your global CSS) for light and dark modes.\n\n## Preview and Code Snippet\n\n<Tabs defaultValue=\"preview\" size=\"sm\" className=\"w-full\" onTabClick={(value) => console.log(\"Tab clicked:\", value)}>\n  <TabsList className=\"grid w-full md:w-[30%] grid-cols-2\">\n    <Tab value=\"preview\">Preview</Tab>\n    <Tab value=\"code\">Code</Tab>\n  </TabsList>\n  <TabsContent value=\"preview\">\n    <Preview>\n      <Tabs defaultValue=\"account\" size=\"sm\" className=\"w-auto\">\n        <TabsList className=\"grid grid-cols-2\">\n          <Tab value=\"account\">Account</Tab>\n          <Tab value=\"password\">Password</Tab>\n        </TabsList>\n        <TabsContent value=\"account\">\n          <div className=\"p-4 border border-[var(--color-border)] rounded-md mt-2\">\n            <h3 className=\"text-lg font-medium\">Account Settings</h3>\n            <p className=\"text-sm text-gray-500 mt-1\">Manage your account settings and preferences.</p>\n          </div>\n        </TabsContent>\n        <TabsContent value=\"password\">\n          <div className=\"p-4 border border-[var(--color-border)] rounded-md mt-2\">\n            <h3 className=\"text-lg font-medium\">Password Settings</h3>\n            <p className=\"text-sm text-gray-500 mt-1\">Change your password and security settings.</p>\n          </div>\n        </TabsContent>\n      </Tabs>\n    </Preview>\n  </TabsContent>\n  <TabsContent value=\"code\">\n    ```tsx\n    import { Tabs, TabsContent, TabsList, Tab } from \"@/components/tabs\";\n    \n    export default function Example() {\n      return (\n        <Tabs defaultValue=\"account\" size=\"sm\" className=\"w-full\">\n          <TabsList className=\"grid grid-cols-2\">\n            <Tab value=\"account\">Account</Tab>\n            <Tab value=\"password\">Password</Tab>\n          </TabsList>\n          <TabsContent value=\"account\">\n            <div className=\"p-4 border border-[var(--color-border)] rounded-md mt-2\">\n              <h3 className=\"text-lg font-medium\">Account Settings</h3>\n              <p className=\"text-sm text-gray-500 mt-1\">Manage your account settings and preferences.</p>\n            </div>\n          </TabsContent>\n          <TabsContent value=\"password\">\n            <div className=\"p-4 border border-[var(--color-border)] rounded-md mt-2\">\n              <h3 className=\"text-lg font-medium\">Password Settings</h3>\n              <p className=\"text-sm text-gray-500 mt-1\">Change your password and security settings.</p>\n            </div>\n          </TabsContent>\n        </Tabs>\n      );\n    }\n    ```\n  </TabsContent>\n</Tabs>\n\n## Props\n\n| Prop            | Type                                   | Default     | Description                                       |\n| --------------- | -------------------------------------- | ----------- | ------------------------------------------------- |\n| `defaultValue`  | `string`                               | `\"\"`        | The initial active tab when the component mounts. |\n| `value`         | `string`                               | `\"\"`        | The controlled value of the active tab.           |\n| `onValueChange` | `(value: string) => void`              | `undefined` | Callback function when the active tab changes.    |\n| `onTabClick`    | `(value: string) => void`              | `undefined` | Callback function when a tab is clicked.          |\n| `size`          | `\"xs\" \\| \"sm\" \\| \"md\" \\| \"lg\" \\| \"xl\"` | `\"md\"`      | Controls the size of the tab buttons.             |\n| `...props`      | `React.HTMLAttributes<HTMLDivElement>` | –           | Supports all standard `div` attributes.           |\n",
    "code": "var Component=(()=>{var m=Object.create;var t=Object.defineProperty;var F=Object.getOwnPropertyDescriptor;var b=Object.getOwnPropertyNames;var g=Object.getPrototypeOf,f=Object.prototype.hasOwnProperty;var v=(n,l)=>()=>(l||n((l={exports:{}}).exports,l),l.exports),B=(n,l)=>{for(var r in l)t(n,r,{get:l[r],enumerable:!0})},i=(n,l,r,s)=>{if(l&&typeof l==\"object\"||typeof l==\"function\")for(let c of b(l))!f.call(n,c)&&c!==r&&t(n,c,{get:()=>l[c],enumerable:!(s=F(l,c))||s.enumerable});return n};var T=(n,l,r)=>(r=n!=null?m(g(n)):{},i(l||!n||!n.__esModule?t(r,\"default\",{value:n,enumerable:!0}):r,n)),C=n=>i(t({},\"__esModule\",{value:!0}),n);var p=v((D,h)=>{h.exports=_jsx_runtime});var x={};B(x,{default:()=>y,frontmatter:()=>w});var e=T(p()),w={title:\"Tabs\",description:\"The Tabs component provides a customizable and smooth tab navigation system, supporting multiple sizes and theme-aware applications, perfect for modern UIs with light and dark modes.\",date:\"2025-03-12\"};function E(n){let l={a:\"a\",code:\"code\",figure:\"figure\",h1:\"h1\",h2:\"h2\",p:\"p\",pre:\"pre\",span:\"span\",strong:\"strong\",table:\"table\",tbody:\"tbody\",td:\"td\",th:\"th\",thead:\"thead\",tr:\"tr\",...n.components},{Preview:r,Tab:s,Tabs:c,TabsContent:o,TabsList:d}=l;return r||a(\"Preview\",!0),s||a(\"Tab\",!0),c||a(\"Tabs\",!0),o||a(\"TabsContent\",!0),d||a(\"TabsList\",!0),(0,e.jsxs)(e.Fragment,{children:[(0,e.jsxs)(l.h1,{id:\"tabs-component-documentation\",children:[(0,e.jsx)(l.a,{className:\"anchor\",href:\"#tabs-component-documentation\",children:(0,e.jsx)(l.span,{className:\"icon icon-link\"})}),\"Tabs Component Documentation\"]}),`\n`,(0,e.jsxs)(l.p,{children:[\"The \",(0,e.jsx)(l.strong,{children:\"Tabs\"}),\" component is a customizable tab system that supports multiple sizes and provides a smooth transition effect. It is designed for modern, theme-aware applications that use CSS variables (defined in your global CSS) for light and dark modes.\"]}),`\n`,(0,e.jsxs)(l.h2,{id:\"preview-and-code-snippet\",children:[(0,e.jsx)(l.a,{className:\"anchor\",href:\"#preview-and-code-snippet\",children:(0,e.jsx)(l.span,{className:\"icon icon-link\"})}),\"Preview and Code Snippet\"]}),`\n`,(0,e.jsxs)(c,{defaultValue:\"preview\",size:\"sm\",className:\"w-full\",onTabClick:u=>console.log(\"Tab clicked:\",u),children:[(0,e.jsxs)(d,{className:\"grid w-full md:w-[30%] grid-cols-2\",children:[(0,e.jsx)(s,{value:\"preview\",children:\"Preview\"}),(0,e.jsx)(s,{value:\"code\",children:\"Code\"})]}),(0,e.jsx)(o,{value:\"preview\",children:(0,e.jsx)(r,{children:(0,e.jsxs)(c,{defaultValue:\"account\",size:\"sm\",className:\"w-auto\",children:[(0,e.jsxs)(d,{className:\"grid grid-cols-2\",children:[(0,e.jsx)(s,{value:\"account\",children:\"Account\"}),(0,e.jsx)(s,{value:\"password\",children:\"Password\"})]}),(0,e.jsx)(o,{value:\"account\",children:(0,e.jsxs)(\"div\",{className:\"p-4 border border-[var(--color-border)] rounded-md mt-2\",children:[(0,e.jsx)(\"h3\",{className:\"text-lg font-medium\",children:\"Account Settings\"}),(0,e.jsx)(\"p\",{className:\"text-sm text-gray-500 mt-1\",children:\"Manage your account settings and preferences.\"})]})}),(0,e.jsx)(o,{value:\"password\",children:(0,e.jsxs)(\"div\",{className:\"p-4 border border-[var(--color-border)] rounded-md mt-2\",children:[(0,e.jsx)(\"h3\",{className:\"text-lg font-medium\",children:\"Password Settings\"}),(0,e.jsx)(\"p\",{className:\"text-sm text-gray-500 mt-1\",children:\"Change your password and security settings.\"})]})})]})})}),(0,e.jsx)(o,{value:\"code\",children:(0,e.jsx)(l.figure,{\"data-rehype-pretty-code-figure\":\"\",children:(0,e.jsx)(l.pre,{tabIndex:\"0\",\"data-language\":\"tsx\",\"data-theme\":\"github-dark\",children:(0,e.jsxs)(l.code,{\"data-language\":\"tsx\",\"data-theme\":\"github-dark\",style:{display:\"grid\"},children:[(0,e.jsxs)(l.span,{\"data-line\":\"\",children:[(0,e.jsx)(l.span,{style:{color:\"#F97583\"},children:\"import\"}),(0,e.jsx)(l.span,{style:{color:\"#E1E4E8\"},children:\" { Tabs, TabsContent, TabsList, Tab } \"}),(0,e.jsx)(l.span,{style:{color:\"#F97583\"},children:\"from\"}),(0,e.jsx)(l.span,{style:{color:\"#9ECBFF\"},children:' \"@/components/tabs\"'}),(0,e.jsx)(l.span,{style:{color:\"#E1E4E8\"},children:\";\"})]}),`\n`,(0,e.jsx)(l.span,{\"data-line\":\"\",children:\" \"}),`\n`,(0,e.jsxs)(l.span,{\"data-line\":\"\",children:[(0,e.jsx)(l.span,{style:{color:\"#F97583\"},children:\"export\"}),(0,e.jsx)(l.span,{style:{color:\"#F97583\"},children:\" default\"}),(0,e.jsx)(l.span,{style:{color:\"#F97583\"},children:\" function\"}),(0,e.jsx)(l.span,{style:{color:\"#B392F0\"},children:\" Example\"}),(0,e.jsx)(l.span,{style:{color:\"#E1E4E8\"},children:\"() {\"})]}),`\n`,(0,e.jsxs)(l.span,{\"data-line\":\"\",children:[(0,e.jsx)(l.span,{style:{color:\"#F97583\"},children:\"  return\"}),(0,e.jsx)(l.span,{style:{color:\"#E1E4E8\"},children:\" (\"})]}),`\n`,(0,e.jsxs)(l.span,{\"data-line\":\"\",children:[(0,e.jsx)(l.span,{style:{color:\"#E1E4E8\"},children:\"    <\"}),(0,e.jsx)(l.span,{style:{color:\"#79B8FF\"},children:\"Tabs\"}),(0,e.jsx)(l.span,{style:{color:\"#B392F0\"},children:\" defaultValue\"}),(0,e.jsx)(l.span,{style:{color:\"#F97583\"},children:\"=\"}),(0,e.jsx)(l.span,{style:{color:\"#9ECBFF\"},children:'\"account\"'}),(0,e.jsx)(l.span,{style:{color:\"#B392F0\"},children:\" size\"}),(0,e.jsx)(l.span,{style:{color:\"#F97583\"},children:\"=\"}),(0,e.jsx)(l.span,{style:{color:\"#9ECBFF\"},children:'\"sm\"'}),(0,e.jsx)(l.span,{style:{color:\"#B392F0\"},children:\" className\"}),(0,e.jsx)(l.span,{style:{color:\"#F97583\"},children:\"=\"}),(0,e.jsx)(l.span,{style:{color:\"#9ECBFF\"},children:'\"w-full\"'}),(0,e.jsx)(l.span,{style:{color:\"#E1E4E8\"},children:\">\"})]}),`\n`,(0,e.jsxs)(l.span,{\"data-line\":\"\",children:[(0,e.jsx)(l.span,{style:{color:\"#E1E4E8\"},children:\"      <\"}),(0,e.jsx)(l.span,{style:{color:\"#79B8FF\"},children:\"TabsList\"}),(0,e.jsx)(l.span,{style:{color:\"#B392F0\"},children:\" className\"}),(0,e.jsx)(l.span,{style:{color:\"#F97583\"},children:\"=\"}),(0,e.jsx)(l.span,{style:{color:\"#9ECBFF\"},children:'\"grid grid-cols-2\"'}),(0,e.jsx)(l.span,{style:{color:\"#E1E4E8\"},children:\">\"})]}),`\n`,(0,e.jsxs)(l.span,{\"data-line\":\"\",children:[(0,e.jsx)(l.span,{style:{color:\"#E1E4E8\"},children:\"        <\"}),(0,e.jsx)(l.span,{style:{color:\"#79B8FF\"},children:\"Tab\"}),(0,e.jsx)(l.span,{style:{color:\"#B392F0\"},children:\" value\"}),(0,e.jsx)(l.span,{style:{color:\"#F97583\"},children:\"=\"}),(0,e.jsx)(l.span,{style:{color:\"#9ECBFF\"},children:'\"account\"'}),(0,e.jsx)(l.span,{style:{color:\"#E1E4E8\"},children:\">Account</\"}),(0,e.jsx)(l.span,{style:{color:\"#79B8FF\"},children:\"Tab\"}),(0,e.jsx)(l.span,{style:{color:\"#E1E4E8\"},children:\">\"})]}),`\n`,(0,e.jsxs)(l.span,{\"data-line\":\"\",children:[(0,e.jsx)(l.span,{style:{color:\"#E1E4E8\"},children:\"        <\"}),(0,e.jsx)(l.span,{style:{color:\"#79B8FF\"},children:\"Tab\"}),(0,e.jsx)(l.span,{style:{color:\"#B392F0\"},children:\" value\"}),(0,e.jsx)(l.span,{style:{color:\"#F97583\"},children:\"=\"}),(0,e.jsx)(l.span,{style:{color:\"#9ECBFF\"},children:'\"password\"'}),(0,e.jsx)(l.span,{style:{color:\"#E1E4E8\"},children:\">Password</\"}),(0,e.jsx)(l.span,{style:{color:\"#79B8FF\"},children:\"Tab\"}),(0,e.jsx)(l.span,{style:{color:\"#E1E4E8\"},children:\">\"})]}),`\n`,(0,e.jsxs)(l.span,{\"data-line\":\"\",children:[(0,e.jsx)(l.span,{style:{color:\"#E1E4E8\"},children:\"      </\"}),(0,e.jsx)(l.span,{style:{color:\"#79B8FF\"},children:\"TabsList\"}),(0,e.jsx)(l.span,{style:{color:\"#E1E4E8\"},children:\">\"})]}),`\n`,(0,e.jsxs)(l.span,{\"data-line\":\"\",children:[(0,e.jsx)(l.span,{style:{color:\"#E1E4E8\"},children:\"      <\"}),(0,e.jsx)(l.span,{style:{color:\"#79B8FF\"},children:\"TabsContent\"}),(0,e.jsx)(l.span,{style:{color:\"#B392F0\"},children:\" value\"}),(0,e.jsx)(l.span,{style:{color:\"#F97583\"},children:\"=\"}),(0,e.jsx)(l.span,{style:{color:\"#9ECBFF\"},children:'\"account\"'}),(0,e.jsx)(l.span,{style:{color:\"#E1E4E8\"},children:\">\"})]}),`\n`,(0,e.jsxs)(l.span,{\"data-line\":\"\",children:[(0,e.jsx)(l.span,{style:{color:\"#E1E4E8\"},children:\"        <\"}),(0,e.jsx)(l.span,{style:{color:\"#85E89D\"},children:\"div\"}),(0,e.jsx)(l.span,{style:{color:\"#B392F0\"},children:\" className\"}),(0,e.jsx)(l.span,{style:{color:\"#F97583\"},children:\"=\"}),(0,e.jsx)(l.span,{style:{color:\"#9ECBFF\"},children:'\"p-4 border border-[var(--color-border)] rounded-md mt-2\"'}),(0,e.jsx)(l.span,{style:{color:\"#E1E4E8\"},children:\">\"})]}),`\n`,(0,e.jsxs)(l.span,{\"data-line\":\"\",children:[(0,e.jsx)(l.span,{style:{color:\"#E1E4E8\"},children:\"          <\"}),(0,e.jsx)(l.span,{style:{color:\"#85E89D\"},children:\"h3\"}),(0,e.jsx)(l.span,{style:{color:\"#B392F0\"},children:\" className\"}),(0,e.jsx)(l.span,{style:{color:\"#F97583\"},children:\"=\"}),(0,e.jsx)(l.span,{style:{color:\"#9ECBFF\"},children:'\"text-lg font-medium\"'}),(0,e.jsx)(l.span,{style:{color:\"#E1E4E8\"},children:\">Account Settings</\"}),(0,e.jsx)(l.span,{style:{color:\"#85E89D\"},children:\"h3\"}),(0,e.jsx)(l.span,{style:{color:\"#E1E4E8\"},children:\">\"})]}),`\n`,(0,e.jsxs)(l.span,{\"data-line\":\"\",children:[(0,e.jsx)(l.span,{style:{color:\"#E1E4E8\"},children:\"          <\"}),(0,e.jsx)(l.span,{style:{color:\"#85E89D\"},children:\"p\"}),(0,e.jsx)(l.span,{style:{color:\"#B392F0\"},children:\" className\"}),(0,e.jsx)(l.span,{style:{color:\"#F97583\"},children:\"=\"}),(0,e.jsx)(l.span,{style:{color:\"#9ECBFF\"},children:'\"text-sm text-gray-500 mt-1\"'}),(0,e.jsx)(l.span,{style:{color:\"#E1E4E8\"},children:\">Manage your account settings and preferences.</\"}),(0,e.jsx)(l.span,{style:{color:\"#85E89D\"},children:\"p\"}),(0,e.jsx)(l.span,{style:{color:\"#E1E4E8\"},children:\">\"})]}),`\n`,(0,e.jsxs)(l.span,{\"data-line\":\"\",children:[(0,e.jsx)(l.span,{style:{color:\"#E1E4E8\"},children:\"        </\"}),(0,e.jsx)(l.span,{style:{color:\"#85E89D\"},children:\"div\"}),(0,e.jsx)(l.span,{style:{color:\"#E1E4E8\"},children:\">\"})]}),`\n`,(0,e.jsxs)(l.span,{\"data-line\":\"\",children:[(0,e.jsx)(l.span,{style:{color:\"#E1E4E8\"},children:\"      </\"}),(0,e.jsx)(l.span,{style:{color:\"#79B8FF\"},children:\"TabsContent\"}),(0,e.jsx)(l.span,{style:{color:\"#E1E4E8\"},children:\">\"})]}),`\n`,(0,e.jsxs)(l.span,{\"data-line\":\"\",children:[(0,e.jsx)(l.span,{style:{color:\"#E1E4E8\"},children:\"      <\"}),(0,e.jsx)(l.span,{style:{color:\"#79B8FF\"},children:\"TabsContent\"}),(0,e.jsx)(l.span,{style:{color:\"#B392F0\"},children:\" value\"}),(0,e.jsx)(l.span,{style:{color:\"#F97583\"},children:\"=\"}),(0,e.jsx)(l.span,{style:{color:\"#9ECBFF\"},children:'\"password\"'}),(0,e.jsx)(l.span,{style:{color:\"#E1E4E8\"},children:\">\"})]}),`\n`,(0,e.jsxs)(l.span,{\"data-line\":\"\",children:[(0,e.jsx)(l.span,{style:{color:\"#E1E4E8\"},children:\"        <\"}),(0,e.jsx)(l.span,{style:{color:\"#85E89D\"},children:\"div\"}),(0,e.jsx)(l.span,{style:{color:\"#B392F0\"},children:\" className\"}),(0,e.jsx)(l.span,{style:{color:\"#F97583\"},children:\"=\"}),(0,e.jsx)(l.span,{style:{color:\"#9ECBFF\"},children:'\"p-4 border border-[var(--color-border)] rounded-md mt-2\"'}),(0,e.jsx)(l.span,{style:{color:\"#E1E4E8\"},children:\">\"})]}),`\n`,(0,e.jsxs)(l.span,{\"data-line\":\"\",children:[(0,e.jsx)(l.span,{style:{color:\"#E1E4E8\"},children:\"          <\"}),(0,e.jsx)(l.span,{style:{color:\"#85E89D\"},children:\"h3\"}),(0,e.jsx)(l.span,{style:{color:\"#B392F0\"},children:\" className\"}),(0,e.jsx)(l.span,{style:{color:\"#F97583\"},children:\"=\"}),(0,e.jsx)(l.span,{style:{color:\"#9ECBFF\"},children:'\"text-lg font-medium\"'}),(0,e.jsx)(l.span,{style:{color:\"#E1E4E8\"},children:\">Password Settings</\"}),(0,e.jsx)(l.span,{style:{color:\"#85E89D\"},children:\"h3\"}),(0,e.jsx)(l.span,{style:{color:\"#E1E4E8\"},children:\">\"})]}),`\n`,(0,e.jsxs)(l.span,{\"data-line\":\"\",children:[(0,e.jsx)(l.span,{style:{color:\"#E1E4E8\"},children:\"          <\"}),(0,e.jsx)(l.span,{style:{color:\"#85E89D\"},children:\"p\"}),(0,e.jsx)(l.span,{style:{color:\"#B392F0\"},children:\" className\"}),(0,e.jsx)(l.span,{style:{color:\"#F97583\"},children:\"=\"}),(0,e.jsx)(l.span,{style:{color:\"#9ECBFF\"},children:'\"text-sm text-gray-500 mt-1\"'}),(0,e.jsx)(l.span,{style:{color:\"#E1E4E8\"},children:\">Change your password and security settings.</\"}),(0,e.jsx)(l.span,{style:{color:\"#85E89D\"},children:\"p\"}),(0,e.jsx)(l.span,{style:{color:\"#E1E4E8\"},children:\">\"})]}),`\n`,(0,e.jsxs)(l.span,{\"data-line\":\"\",children:[(0,e.jsx)(l.span,{style:{color:\"#E1E4E8\"},children:\"        </\"}),(0,e.jsx)(l.span,{style:{color:\"#85E89D\"},children:\"div\"}),(0,e.jsx)(l.span,{style:{color:\"#E1E4E8\"},children:\">\"})]}),`\n`,(0,e.jsxs)(l.span,{\"data-line\":\"\",children:[(0,e.jsx)(l.span,{style:{color:\"#E1E4E8\"},children:\"      </\"}),(0,e.jsx)(l.span,{style:{color:\"#79B8FF\"},children:\"TabsContent\"}),(0,e.jsx)(l.span,{style:{color:\"#E1E4E8\"},children:\">\"})]}),`\n`,(0,e.jsxs)(l.span,{\"data-line\":\"\",children:[(0,e.jsx)(l.span,{style:{color:\"#E1E4E8\"},children:\"    </\"}),(0,e.jsx)(l.span,{style:{color:\"#79B8FF\"},children:\"Tabs\"}),(0,e.jsx)(l.span,{style:{color:\"#E1E4E8\"},children:\">\"})]}),`\n`,(0,e.jsx)(l.span,{\"data-line\":\"\",children:(0,e.jsx)(l.span,{style:{color:\"#E1E4E8\"},children:\"  );\"})}),`\n`,(0,e.jsx)(l.span,{\"data-line\":\"\",children:(0,e.jsx)(l.span,{style:{color:\"#E1E4E8\"},children:\"}\"})})]})})})})]}),`\n`,(0,e.jsxs)(l.h2,{id:\"props\",children:[(0,e.jsx)(l.a,{className:\"anchor\",href:\"#props\",children:(0,e.jsx)(l.span,{className:\"icon icon-link\"})}),\"Props\"]}),`\n`,(0,e.jsxs)(l.table,{children:[(0,e.jsx)(l.thead,{children:(0,e.jsxs)(l.tr,{children:[(0,e.jsx)(l.th,{children:\"Prop\"}),(0,e.jsx)(l.th,{children:\"Type\"}),(0,e.jsx)(l.th,{children:\"Default\"}),(0,e.jsx)(l.th,{children:\"Description\"})]})}),(0,e.jsxs)(l.tbody,{children:[(0,e.jsxs)(l.tr,{children:[(0,e.jsx)(l.td,{children:(0,e.jsx)(l.code,{children:\"defaultValue\"})}),(0,e.jsx)(l.td,{children:(0,e.jsx)(l.code,{children:\"string\"})}),(0,e.jsx)(l.td,{children:(0,e.jsx)(l.code,{children:'\"\"'})}),(0,e.jsx)(l.td,{children:\"The initial active tab when the component mounts.\"})]}),(0,e.jsxs)(l.tr,{children:[(0,e.jsx)(l.td,{children:(0,e.jsx)(l.code,{children:\"value\"})}),(0,e.jsx)(l.td,{children:(0,e.jsx)(l.code,{children:\"string\"})}),(0,e.jsx)(l.td,{children:(0,e.jsx)(l.code,{children:'\"\"'})}),(0,e.jsx)(l.td,{children:\"The controlled value of the active tab.\"})]}),(0,e.jsxs)(l.tr,{children:[(0,e.jsx)(l.td,{children:(0,e.jsx)(l.code,{children:\"onValueChange\"})}),(0,e.jsx)(l.td,{children:(0,e.jsx)(l.code,{children:\"(value: string) => void\"})}),(0,e.jsx)(l.td,{children:(0,e.jsx)(l.code,{children:\"undefined\"})}),(0,e.jsx)(l.td,{children:\"Callback function when the active tab changes.\"})]}),(0,e.jsxs)(l.tr,{children:[(0,e.jsx)(l.td,{children:(0,e.jsx)(l.code,{children:\"onTabClick\"})}),(0,e.jsx)(l.td,{children:(0,e.jsx)(l.code,{children:\"(value: string) => void\"})}),(0,e.jsx)(l.td,{children:(0,e.jsx)(l.code,{children:\"undefined\"})}),(0,e.jsx)(l.td,{children:\"Callback function when a tab is clicked.\"})]}),(0,e.jsxs)(l.tr,{children:[(0,e.jsx)(l.td,{children:(0,e.jsx)(l.code,{children:\"size\"})}),(0,e.jsx)(l.td,{children:(0,e.jsx)(l.code,{children:'\"xs\" | \"sm\" | \"md\" | \"lg\" | \"xl\"'})}),(0,e.jsx)(l.td,{children:(0,e.jsx)(l.code,{children:'\"md\"'})}),(0,e.jsx)(l.td,{children:\"Controls the size of the tab buttons.\"})]}),(0,e.jsxs)(l.tr,{children:[(0,e.jsx)(l.td,{children:(0,e.jsx)(l.code,{children:\"...props\"})}),(0,e.jsx)(l.td,{children:(0,e.jsx)(l.code,{children:\"React.HTMLAttributes<HTMLDivElement>\"})}),(0,e.jsx)(l.td,{children:\"\\u2013\"}),(0,e.jsxs)(l.td,{children:[\"Supports all standard \",(0,e.jsx)(l.code,{children:\"div\"}),\" attributes.\"]})]})]})]})]})}function y(n={}){let{wrapper:l}=n.components||{};return l?(0,e.jsx)(l,{...n,children:(0,e.jsx)(E,{...n})}):E(n)}function a(n,l){throw new Error(\"Expected \"+(l?\"component\":\"object\")+\" `\"+n+\"` to be defined: you likely forgot to import, pass, or provide it.\")}return C(x);})();\n;return Component;"
  },
  "_id": "components/tabs.mdx",
  "_raw": {
    "sourceFilePath": "components/tabs.mdx",
    "sourceFileName": "tabs.mdx",
    "sourceFileDir": "components",
    "contentType": "mdx",
    "flattenedPath": "components/tabs"
  },
  "type": "Doc",
  "url": "/docs/components/tabs",
  "urlPath": "components/tabs"
}